mcp_add_project/__init__.py
mcp_add_project-0.1.0.dist-info/WHEEL
mcp_add_project-0.1.0.dist-info/entry_points.txt
mcp_add_project-0.1.0.dist-info/METADATA
mcp_add_project-0.1.0.dist-info/RECORD
