Metadata-Version: 2.3
Name: mcp-add-project
Version: 0.1.0
Summary: Add your description here
Author: macxiang
Author-email: macxiang <xiangzp2017@163.com>
Requires-Dist: mcp[cli]>=1.12.4
Requires-Python: >=3.12
